radiominer/__init__.py
radiominer/cli.py
radiominer/main.py
radiominer/version.py
test/__init__.py
test/test_edge_cases.py
test/test_file_monitor.py
test/test_full_cycle.py
test/test_logging.py
test/test_radiorecoder.py
test/test_record_transcribe_flags.py
test/test_recorder.py
test/test_transcription.py
radiominer-1.1.9.dist-info/LICENSE
radiominer-1.1.9.dist-info/METADATA
radiominer-1.1.9.dist-info/WHEEL
radiominer-1.1.9.dist-info/entry_points.txt
radiominer-1.1.9.dist-info/top_level.txt
radiominer-1.1.9.dist-info/RECORD
