Metadata-Version: 2.1
Name: radiominer
Version: 1.1.9
Summary: A radio streaming and transcription application.
Author: Sebastian Milchsack
Author-email: info@milchsack.com
Classifier: Programming Language :: Python :: 3
Classifier: License :: OSI Approved :: MIT License
Classifier: Operating System :: OS Independent
Requires-Python: >=3.10
License-File: LICENSE
Requires-Dist: openai-whisper
Requires-Dist: ffmpeg-python
Requires-Dist: numpy
Requires-Dist: colorama
